odoo/addons/shopinvader_product_video_link/README.rst
odoo/addons/shopinvader_product_video_link/__init__.py
odoo/addons/shopinvader_product_video_link/__manifest__.py
odoo/addons/shopinvader_product_video_link/data/ir_export_category.xml
odoo/addons/shopinvader_product_video_link/data/ir_export_product.xml
odoo/addons/shopinvader_product_video_link/i18n/shopinvader_product_video_link.pot
odoo/addons/shopinvader_product_video_link/readme/CONTRIBUTORS.rst
odoo/addons/shopinvader_product_video_link/readme/CREDITS.rst
odoo/addons/shopinvader_product_video_link/readme/DESCRIPTION.rst
odoo/addons/shopinvader_product_video_link/static/description/index.html
odoo14_addon_shopinvader_product_video_link-14.0.1.0.2.dist-info/METADATA
odoo14_addon_shopinvader_product_video_link-14.0.1.0.2.dist-info/WHEEL
odoo14_addon_shopinvader_product_video_link-14.0.1.0.2.dist-info/top_level.txt
odoo14_addon_shopinvader_product_video_link-14.0.1.0.2.dist-info/RECORD
